{"cameraMode":{"drawMode":0,"name":"Shaded","section":"Shading Mode"},"sceneLighting":true,"audioPlay":false,"sceneViewState":{"m_AlwaysRefresh":false,"showFog":true,"showSkybox":true,"showFlares":true,"showImageEffects":true,"showParticleSystems":true,"showVisualEffectGraphs":true,"m_FxEnabled":true},"in2DMode":false,"pivot":{"x":3.156471014022827,"y":14.955649375915528,"z":-0.7386125326156616},"rotation":{"x":0.027718814089894296,"y":0.9026934504508972,"z":0.058856286108493808,"w":-0.4253911077976227},"size":1.5974386930465699,"orthographic":false}